github_dlr/__init__.py
github_dlr/console.py
github_dlr/loader.py
github_dlr/source.py
github_dlr-0.1.2.dist-info/LICENSE
github_dlr-0.1.2.dist-info/METADATA
github_dlr-0.1.2.dist-info/WHEEL
github_dlr-0.1.2.dist-info/entry_points.txt
github_dlr-0.1.2.dist-info/RECORD
