Metadata-Version: 2.1
Name: github-dlr
Version: 0.1.2
Summary: Download individual files and folders from Github
Home-page: https://github.com/rocktimsaikia/github-dlr
Keywords: download,github,directory,gitdown
Author: Rocktim Saikia
Author-email: rocktimthedev@gmail.com
Requires-Python: >=3.8,<4.0
Classifier: Environment :: Console
Classifier: Programming Language :: Python :: 3
Classifier: Programming Language :: Python :: 3.8
Classifier: Programming Language :: Python :: 3.9
Classifier: Programming Language :: Python :: 3.10
Classifier: Programming Language :: Python :: 3.11
Classifier: Programming Language :: Python :: 3.12
Requires-Dist: aiohttp (>=3.10.5,<4.0.0)
Requires-Dist: alive-progress (>=3.1.5,<4.0.0)
Requires-Dist: argparse (>=1.4.0,<2.0.0)
Requires-Dist: emoji (>=2.12.1,<3.0.0)
